ansible_nwd/__init__.py
ansible_nwd/main.py
ansible_nwd/markdown.j2
ansible_nwd/parsing/__init__.py
ansible_nwd/parsing/parsing.py
ansible_nwd/utilities/__init__.py
ansible_nwd/utilities/utilities.py
ansible_nwd-0.8.data/data/ansible_nwd/markdown.j2
ansible_nwd-0.8.dist-info/LICENSE.TXT
ansible_nwd-0.8.dist-info/METADATA
ansible_nwd-0.8.dist-info/WHEEL
ansible_nwd-0.8.dist-info/entry_points.txt
ansible_nwd-0.8.dist-info/top_level.txt
ansible_nwd-0.8.dist-info/RECORD
