Metadata-Version: 2.1
Name: ansible-nwd
Version: 0.8
Summary: Ansible role automatic documentation
Home-page: https://github.com/VasseurLaurent/ansible-nwd
Author: VASSEUR Laurent
Author-email: mail.laurentvasseur@gmail.com
License: MIT License
Download-URL: https://github.com/VasseurLaurent/ansible-nwd/archive/v0.7.tar.gz
Keywords: ansible,documentation,automation
Platform: UNKNOWN
Classifier: Development Status :: 3 - Alpha
Classifier: Intended Audience :: Developers
Classifier: Topic :: Software Development :: Build Tools
Classifier: License :: OSI Approved :: MIT License
Classifier: Programming Language :: Python :: 3.6
Classifier: Intended Audience :: Information Technology
Classifier: Intended Audience :: System Administrators
Classifier: Environment :: Console
Classifier: Topic :: System :: Systems Administration
Classifier: Topic :: Utilities
Classifier: Topic :: Documentation
Requires-Python: >=3.6
Requires-Dist: ruamel.yaml
Requires-Dist: ruamel.yaml.clib
Requires-Dist: jinja2-time
